source_google_drive/__init__.py
source_google_drive/exceptions.py
source_google_drive/run.py
source_google_drive/schemas/file_permissions.json
source_google_drive/schemas/identities.json
source_google_drive/source.py
source_google_drive/spec.py
source_google_drive/stream_permissions_reader.py
source_google_drive/stream_reader.py
source_google_drive/utils.py
airbyte_source_google_drive-0.5.9.dist-info/METADATA
airbyte_source_google_drive-0.5.9.dist-info/WHEEL
airbyte_source_google_drive-0.5.9.dist-info/entry_points.txt
airbyte_source_google_drive-0.5.9.dist-info/RECORD
