Metadata-Version: 2.1
Name: airbyte-source-google-drive
Version: 0.5.9
Summary: Source implementation for Google Drive.
Home-page: https://airbyte.com
License: ELv2
Author: Airbyte
Author-email: contact@airbyte.io
Requires-Python: >=3.10,<3.14
Classifier: License :: Other/Proprietary License
Classifier: Programming Language :: Python :: 3
Classifier: Programming Language :: Python :: 3.10
Classifier: Programming Language :: Python :: 3.11
Classifier: Programming Language :: Python :: 3.12
Classifier: Programming Language :: Python :: 3.13
Requires-Dist: airbyte-cdk[file-based] (>=7.0.1,<8.0.0)
Requires-Dist: google-api-python-client (==2.104.0)
Requires-Dist: google-api-python-client-stubs (==1.18.0)
Requires-Dist: google-auth-httplib2 (==0.1.1)
Requires-Dist: google-auth-oauthlib (==1.1.0)
Project-URL: Documentation, https://docs.airbyte.com/integrations/sources/google-drive
Project-URL: Repository, https://github.com/airbytehq/airbyte
